Metadata-Version: 2.1
Name: UltimateSwitchCase
Version: 0.1
Summary: Switch case functionality for python
Home-page: https://github.com/F4hhc/UltimateSwitchCase
Author: Tommaso Sollo
Author-email: tommaso.sollo06@gmail.com
License: MIT
Download-URL: https://github.com/F4hhc/UltimateSwitchCase/v_01.tar.gz
Keywords: Switch,Case,switchcase,UltimateSwitchCase
Platform: UNKNOWN
Classifier: Development Status :: 3 - Alpha
Classifier: Intended Audience :: Developers
Classifier: Topic :: Software Development :: Build Tools
Classifier: License :: OSI Approved :: MIT License
Classifier: Programming Language :: Python :: 3
Classifier: Programming Language :: Python :: 3.4
Classifier: Programming Language :: Python :: 3.5
Classifier: Programming Language :: Python :: 3.6
Classifier: Programming Language :: Python :: 3.7
Classifier: Programming Language :: Python :: 3.8
Classifier: Programming Language :: Python :: 3.9
Classifier: Programming Language :: Python :: 3.10
